{
  "suite_version": "2026-07-19.1",
  "manifest_version": "2026-07-19.1",
  "provider": "acedata-self-hosted",
  "mode": "raw",
  "total": 53,
  "passed": 25,
  "failed": 28,
  "passed_case_ids": [
    "CORE-001",
    "CORE-002",
    "CORE-003",
    "CORE-004",
    "CORE-005",
    "CORE-006",
    "CORE-007",
    "CORE-008",
    "CORE-009",
    "CORE-010",
    "CORE-011",
    "CORE-012",
    "CORE-013",
    "CORE-014",
    "SETTLE-001",
    "SETTLE-002",
    "SETTLE-003",
    "SETTLE-004",
    "SETTLE-007",
    "VERIFY-001",
    "VERIFY-002",
    "VERIFY-003",
    "VERIFY-004",
    "VERIFY-009",
    "VERIFY-010"
  ],
  "failed_case_ids": [
    "NEG-001",
    "NEG-002",
    "NEG-003",
    "NEG-004",
    "NEG-005",
    "NEG-006",
    "NEG-007",
    "NEG-008",
    "NEG-009",
    "NEG-010",
    "NEG-011",
    "NEG-012",
    "NEG-013",
    "NEG-014",
    "NEG-015",
    "NEG-016",
    "SETTLE-005",
    "SETTLE-006",
    "SETTLE-008",
    "SETTLE-009",
    "SETTLE-010",
    "SNEG-001",
    "SNEG-002",
    "SNEG-003",
    "VERIFY-005",
    "VERIFY-006",
    "VERIFY-007",
    "VERIFY-008"
  ],
  "non_protocol_statuses": 0,
  "evidence": "Local Python 3.10 Facilitator, isolated SQLite, chain-id-only RPC; no external broadcast."
}
